README.md
setup.py
RandKey/RandKey.py
RandKey/__init__.py
RandKey.egg-info/PKG-INFO
RandKey.egg-info/SOURCES.txt
RandKey.egg-info/dependency_links.txt
RandKey.egg-info/top_level.txt