Metadata-Version: 2.1
Name: RandKey
Version: 1.0.2
Summary: A useful key generator.
Home-page: UNKNOWN
Author: JasonTheDev
Author-email: examqiename@gmail.com
License: UNKNOWN
Platform: UNKNOWN
Classifier: Programming Language :: Python :: 3
Requires-Python: >=3.6
